{
  "animateLoading": true,
  "borderRadius": "{{appsmith.theme.borderRadius.appBorderRadius}}",
  "bottomRow": 8,
  "boxShadow": "none",
  "buttonColor": "{{appsmith.theme.colors.primaryColor}}",
  "buttonVariant": "PRIMARY",
  "displayName": "Icon button",
  "dynamicBindingPathList": [
    {
      "key": "buttonColor"
    },
    {
      "key": "borderRadius"
    }
  ],
  "dynamicPropertyPathList": [],
  "dynamicTriggerPathList": [
    {
      "key": "onClick"
    }
  ],
  "hideCard": false,
  "iconName": "refresh",
  "iconSVG": "/static/media/icon.b08054586989b185a0801e9a34f8ad49.svg",
  "isDeprecated": false,
  "isDisabled": false,
  "isLoading": false,
  "isVisible": true,
  "key": "m7cdwf2gwi",
  "leftColumn": 40,
  "minWidth": 50,
  "mobileBottomRow": 22,
  "mobileLeftColumn": 26,
  "mobileRightColumn": 30,
  "mobileTopRow": 18,
  "onClick": "{{getAllProspects.run().then(() => {\n  showAlert('Daten wurden aktualisiert', 'success');\n}).catch(() => {\n  showAlert('Fehler bei der Datenbankverbindung', '');\n});}}",
  "originalBottomRow": 24,
  "originalTopRow": 18,
  "parentColumnSpace": 19.09375,
  "parentId": "sirbr29l7j",
  "parentRowSpace": 10,
  "renderMode": "CANVAS",
  "responsiveBehavior": "hug",
  "rightColumn": 43,
  "searchTags": [
    "click",
    "submit"
  ],
  "tags": [
    "Buttons"
  ],
  "topRow": 2,
  "type": "ICON_BUTTON_WIDGET",
  "version": 1,
  "widgetId": "fk4ro2jsck",
  "widgetName": "refresh_all_data"
}